emucorebrain/consts/__init__.py
emucorebrain/consts/consts.py
emucorebrain/core/__init__.py
emucorebrain/core/predictor.py
emucorebrain/core/preprocessor.py
emucorebrain/core/trainer.py
emucorebrain/data/abstracts/TaskExecutor.py
emucorebrain/data/abstracts/__init__.py
emucorebrain/data/carriers/__init__.py
emucorebrain/data/carriers/carrier.py
emucorebrain/data/carriers/ins_mechanism.py
emucorebrain/data/carriers/outs_mechanism.py
emucorebrain/data/carriers/string.py
emucorebrain/data/containers/__init__.py
emucorebrain/data/containers/lockers.py
emucorebrain/data/containers/settings.py
emucorebrain/data/models/__init__.py
emucorebrain/data/models/lockers.py
emucorebrain/data/models/route_model.py
emucorebrain/io/__init__.py
emucorebrain/io/mechanisms/__init__.py
emucorebrain/io/mechanisms/ins_mechanism.py
emucorebrain/io/mechanisms/outs_mechanism.py
emucorebrain/keywords/__init__.py
emucorebrain/keywords/model.py
emucorebrain/keywords/process.py
emucorebrain/keywords/task_executor.py
emucorebrain/processes/__init__.py
emucorebrain/processes/core.py
emucorebrain/processes/namespace.py
emucorebrain-0.5.6.dist-info/METADATA
emucorebrain-0.5.6.dist-info/WHEEL
emucorebrain-0.5.6.dist-info/top_level.txt
emucorebrain-0.5.6.dist-info/RECORD
