Metadata-Version: 2.1
Name: emucorebrain
Version: 0.5.6
Summary: Brain of EmulationCore
Home-page: https://github.com/GENIVI/GENIVI-GSoC-18/tree/master/Brain/core
Author: Chandeepa Dissanayake
Author-email: chandeepadissanayake@gmail.com
License: Mozilla Public License 2.0
Platform: UNKNOWN
Requires-Dist: nltk (==3.3)
